soilstat/__init__.py
soilstat/bearing_capacity/__init__.py
soilstat/bearing_capacity/vesic.py
soilstat/liquefaction/__init__.py
soilstat/liquefaction/spt/__init__.py
soilstat/liquefaction/spt/idriss.py
soilstat-0.0.19.dist-info/LICENSE
soilstat-0.0.19.dist-info/METADATA
soilstat-0.0.19.dist-info/WHEEL
soilstat-0.0.19.dist-info/top_level.txt
soilstat-0.0.19.dist-info/RECORD
