Metadata-Version: 2.1
Name: soilstat
Version: 0.0.19
Summary: A toolbox for geotechnical engineering calculations
Home-page: https://github.com/nubufi/soilstat
Author: Numan Burak Fidan
Author-email: numanburakfidan@yandex.com
Classifier: Programming Language :: Python :: 3
Classifier: License :: OSI Approved :: MIT License
Classifier: Operating System :: OS Independent
Requires-Python: >=3.6
License-File: LICENSE
Requires-Dist: numpy
